adstractai/__init__.py
adstractai/client.py
adstractai/constants.py
adstractai/errors.py
adstractai/models.py
adstractai/py.typed
adstractai-0.0.4.dist-info/METADATA
adstractai-0.0.4.dist-info/WHEEL
adstractai-0.0.4.dist-info/licenses/LICENSE
adstractai-0.0.4.dist-info/RECORD
