Metadata-Version: 2.4
Name: adstractai
Version: 0.0.4
Summary: Ad network that delivers ads to the LLM's response
Project-URL: Homepage, https://github.com/Adstract-AI/adstract-library
Project-URL: Repository, https://github.com/Adstract-AI/adstract-library
Project-URL: Issues, https://github.com/Adstract-AI/adstract-library/issues
Author-email: Nikola Jagurinoski <jagurinoskini@gmail.com>, Viktor Kostadinoski <kostadinoskiviktor@yahoo.com>, Andrea Stevanoska <andrea.stevanoska2@gmail.com>, Darko Petrushevski <petrusevskidare@gmail.com>, Gorazd Filpovski <gorazdfilipovski@gmail.com>
License: MIT
License-File: LICENSE
Keywords: ad-network,ad-serving,ads,llm
Classifier: Development Status :: 3 - Alpha
Classifier: Intended Audience :: Developers
Classifier: License :: OSI Approved :: MIT License
Classifier: Programming Language :: Python
Classifier: Programming Language :: Python :: 3
Classifier: Programming Language :: Python :: 3 :: Only
Classifier: Programming Language :: Python :: 3.10
Classifier: Programming Language :: Python :: 3.11
Classifier: Programming Language :: Python :: 3.12
Classifier: Typing :: Typed
Requires-Python: >=3.10
Requires-Dist: httpx>=0.27.0
Requires-Dist: pydantic>=2.0.0
Provides-Extra: dev
Requires-Dist: build>=1.2.1; extra == 'dev'
Requires-Dist: pre-commit>=3.7.1; extra == 'dev'
Requires-Dist: pyright>=1.1.376; extra == 'dev'
Requires-Dist: pytest>=8.2.2; extra == 'dev'
Requires-Dist: ruff>=0.6.5; extra == 'dev'
